standardweb3/__init__.py
standardweb3/py.typed
standardweb3/abis/matching_engine.py
standardweb3/api/query/__init__.py
standardweb3/consts/__init__.py
standardweb3/consts/contracts.py
standardweb3/consts/urls.py
standardweb3/contract/__init__.py
standardweb3/examples/README.md
standardweb3/examples/WEBSOCKET_README.md
standardweb3/examples/api.py
standardweb3/examples/batch_orders_example.py
standardweb3/examples/bot.py
standardweb3/examples/eth_trading_example.py
standardweb3/examples/match_trade.py
standardweb3/examples/return_values_example.py
standardweb3/examples/simple_trading.py
standardweb3/examples/simple_websocket_example.py
standardweb3/examples/spot_bars_example.py
standardweb3/examples/spot_orderbook_example.py
standardweb3/examples/spot_orderhistories_example.py
standardweb3/examples/spot_orders_example.py
standardweb3/examples/spot_trades_example.py
standardweb3/examples/trading.py
standardweb3/examples/websocket_example.py
standardweb3/types/__init__.py
standardweb3/types/streams/__init__.py
standardweb3/types/streams/bars/__init__.py
standardweb3/types/streams/bars/spot.py
standardweb3/types/streams/orderbook/__init__.py
standardweb3/types/streams/orderbook/spot.py
standardweb3/types/streams/orderhistories/__init__.py
standardweb3/types/streams/orderhistories/spot.py
standardweb3/types/streams/orders/__init__.py
standardweb3/types/streams/orders/spot.py
standardweb3/types/streams/trades/__init__.py
standardweb3/types/streams/trades/spot.py
standardweb3/ws/__init__.py
standardweb3-0.0.13.dist-info/METADATA
standardweb3-0.0.13.dist-info/WHEEL
standardweb3-0.0.13.dist-info/licenses/LICENSE
standardweb3-0.0.13.dist-info/RECORD
