Metadata-Version: 2.4
Name: standardweb3
Version: 0.0.13
Summary: Python Client for Standard
Author-email: Hyungsuk Kang <hskang9@gmail.com>
License-File: LICENSE
Requires-Python: >=3.10
Requires-Dist: aiohttp>=3.11.11
Requires-Dist: asyncio>=3.4.3
Requires-Dist: eth-abi>=5.1.0
Requires-Dist: eth-account>=0.13.4
Requires-Dist: eth-typing>=5.1.0
Requires-Dist: eth-utils>=5.1.0
Requires-Dist: httpx>=0.28.1
Requires-Dist: pre-commit>=4.0.1
Requires-Dist: pydantic>=2.10.5
Requires-Dist: python-dotenv>=1.0.1
Requires-Dist: web3>=7.6.1
Requires-Dist: websockets>=13.1
